{
    "workouts": [
    {
    "name": "Lunges",
    "difficulty": "Easy",
    "duration": "15 mins",
    "image": "https://imagesvc.meredithcorp.io/v3/mm/image?url=https%3A%2F%2Fstatic.onecms.io%2Fwp-content%2Fuploads%2Fsites%2F35%2F2020%2F05%2F04%2Fcardio-workout-at-home-bridge-2000.jpg"
    }, {
    "name": "Pushups",
    "difficulty": "Hard",
    "duration": "45 mins",
    "image": "https://cdn3.vectorstock.com/i/1000x1000/66/17/fitness-gym-graphic-design-template-isolated-vector-30176617.jpg"
    }, 
    {
    "name": "Swim",
    "difficulty": "Easy",
    "duration": "30 mins",
    "image": "https://cdn3.vectorstock.com/i/1000x1000/66/17/fitness-gym-graphic-design-template-isolated-vector-30176617.jpg"
    }, 
    {
    "name": "Bench",
    "difficulty": "Moderate",
    "duration": "60 mins",
    "image": "https://www.creativefabrica.com/wp-content/uploads/2018/12/Dumbbell-by-khld939-580x386.jpg"
    }, 
    {
    "name": "Treadmill",
    "difficulty": "Easy",
    "duration": "30 mins",
    "image": "https://cdn3.vectorstock.com/i/1000x1000/66/17/fitness-gym-graphic-design-template-isolated-vector-30176617.jpg"
    }, 
    {
    "name": "Deadlifts",
    "difficulty": "Moderate",
    "duration": "15 mins",
    "image": "https://www.creativefabrica.com/wp-content/uploads/2018/12/Dumbbell-by-khld939-580x386.jpg"
    }, 
    {
    "name": "Burpees",
    "difficulty": "Hard",
    "duration": "60 mins",
    "image": "https://cdn3.vectorstock.com/i/1000x1000/66/17/fitness-gym-graphic-design-template-isolated-vector-30176617.jpg"
    }, 
    {
    "name": "Crunches",
    "difficulty": "Easy",
    "duration": "45 mins",
    "image": "https://imagesvc.meredithcorp.io/v3/mm/image?url=https%3A%2F%2Fstatic.onecms.io%2Fwp-content%2Fuploads%2Fsites%2F35%2F2020%2F05%2F04%2Fcardio-workout-at-home-bridge-2000.jpg"
    },
    {
        "name": "Squats",
        "difficulty": "Easy",
        "duration": "15 mins",
        "image": "https://www.creativefabrica.com/wp-content/uploads/2018/12/Dumbbell-by-khld939-580x386.jpg"
        }, {
        "name": "Pullups",
        "difficulty": "Hard",
        "duration": "45 mins",
        "image": "https://cdn3.vectorstock.com/i/1000x1000/66/17/fitness-gym-graphic-design-template-isolated-vector-30176617.jpg"
        }, 
        {
        "name": "Hike",
        "difficulty": "Easy",
        "duration": "60 mins",
        "image": "https://imagesvc.meredithcorp.io/v3/mm/image?url=https%3A%2F%2Fstatic.onecms.io%2Fwp-content%2Fuploads%2Fsites%2F35%2F2020%2F05%2F04%2Fcardio-workout-at-home-bridge-2000.jpg"
        }, 
        {
        "name": "Bike",
        "difficulty": "Moderate",
        "duration": "30 mins",
        "image": "https://www.creativefabrica.com/wp-content/uploads/2018/12/Dumbbell-by-khld939-580x386.jpg"
        }
    ],
    "users": [
    {
    "name": "",
    "email": "",
    "password": ""
    }
    ],
    "completed-workouts": [
    {
    "name": "Mountain Biking",
    "date": "3 Days Ago"    
    },
    {
    "name": "KickBoxing",
    "date": "1 Week Ago"    
    },
    {
    "name": "H.I.I.T",
    "date": "1 Week Ago"    
    },
    {
    "name": "Sprints",
    "date": "1 Week Ago"    
    },
    {
    "name": "Rowing",
    "date": "2 Weeks Ago"    
    }
    ]
}